bisectsearch/README.MD
bisectsearch/__init__.py
bisectsearch/requirements.txt
bisectsearch/thirdparty.json
bisectsearch-0.11.dist-info/LICENSE.rst
bisectsearch-0.11.dist-info/METADATA
bisectsearch-0.11.dist-info/WHEEL
bisectsearch-0.11.dist-info/top_level.txt
bisectsearch-0.11.dist-info/RECORD
