Metadata-Version: 2.1
Name: bisectsearch
Version: 0.11
Summary: Functions for performing binary search on sorted lists
Home-page: https://github.com/hansalemaos/bisectsearch
Author: Johannes Fischer
Author-email: aulasparticularesdealemaosp@gmail.com
License: MIT
Keywords: bisect,search
Classifier: Development Status :: 4 - Beta
Classifier: Programming Language :: Python :: 3 :: Only
Classifier: Programming Language :: Python :: 3.10
Classifier: Topic :: Software Development :: Libraries :: Python Modules
Classifier: Topic :: Utilities
License-File: LICENSE.rst
